alexscan/VERSION
alexscan/__init__.py
alexscan/__main__.py
alexscan/cli.py
alexscan/analyzers/__init__.py
alexscan/analyzers/base.py
alexscan/analyzers/blocklist.py
alexscan/analyzers/crawler.py
alexscan/analyzers/dga.py
alexscan/analyzers/dns.py
alexscan/analyzers/headers.py
alexscan/analyzers/hierarchical_classification.py
alexscan/analyzers/llm_summary.py
alexscan/analyzers/port_scanner.py
alexscan/analyzers/report_generator.py
alexscan/analyzers/safety_rating.py
alexscan/analyzers/screenshot.py
alexscan/analyzers/ssl.py
alexscan/analyzers/whitelist.py
alexscan/analyzers/whois.py
alexscan/utils/__init__.py
alexscan/utils/cache_manager.py
alexscan/utils/report_utils.py
alexscan/utils/validators.py
alexscan-0.1.6.dist-info/licenses/LICENSE
alexscan-0.1.6.dist-info/METADATA
alexscan-0.1.6.dist-info/WHEEL
alexscan-0.1.6.dist-info/entry_points.txt
alexscan-0.1.6.dist-info/top_level.txt
alexscan-0.1.6.dist-info/RECORD
