Metadata-Version: 2.4
Name: alexscan
Version: 0.1.6
Summary: Comprehensive domain security analysis tool with AI-powered insights
Home-page: https://github.com/alexevan/alexscan
Author: Alex Evan
Author-email: Alex Christian <13alexchristian@gmail.com>
License: MIT
Project-URL: Homepage, https://github.com/alexevan13/domain-analyzer
Project-URL: Repository, https://github.com/alexevan13/domain-analyzer
Project-URL: Documentation, https://github.com/alexevan13/domain-analyzer#readme
Project-URL: Issues, https://github.com/alexevan13/domain-analyzer/issues
Project-URL: Changelog, https://github.com/alexevan13/domain-analyzer/blob/main/README.md#release-notes
Keywords: security,domain,analysis,dns,whois,ssl,malware,dga,cybersecurity
Classifier: Development Status :: 4 - Beta
Classifier: Intended Audience :: System Administrators
Classifier: Intended Audience :: Information Technology
Classifier: License :: OSI Approved :: MIT License
Classifier: Operating System :: OS Independent
Classifier: Programming Language :: Python :: 3
Classifier: Programming Language :: Python :: 3.9
Classifier: Programming Language :: Python :: 3.10
Classifier: Programming Language :: Python :: 3.11
Classifier: Topic :: Internet :: Name Service (DNS)
Classifier: Topic :: System :: Systems Administration
Classifier: Topic :: Security
Classifier: Topic :: Utilities
Requires-Python: >=3.8
License-File: LICENSE
Requires-Dist: typer>=0.9.0
Requires-Dist: rich>=13.0.0
Provides-Extra: dev
Requires-Dist: pytest>=7.0.0; extra == "dev"
Requires-Dist: black>=22.0.0; extra == "dev"
Requires-Dist: flake8>=4.0.0; extra == "dev"
Requires-Dist: mypy>=0.950; extra == "dev"
Dynamic: author
Dynamic: home-page
Dynamic: license-file
Dynamic: requires-python
